<?xml version="1.0" encoding="UTF-8"?>
<LanguageData>

	<!--========= General ============-->
	
	<Goto.reportString>In movimento.</Goto.reportString>
	
	<Wait.reportString>In piedi.</Wait.reportString> <!-- probably can be better -->
	
	<AttackStatic.reportString>Attaccando TargetA.</AttackStatic.reportString>
	
	<AttackMelee.reportString>Attaccando in corpo a corpo TargetA.</AttackMelee.reportString>
	
	<UseVerbOnThing.reportString>Usando verb.</UseVerbOnThing.reportString> <!-- NOT TESTED -->
	
	<Equip.reportString>Equipaggiando TargetA.</Equip.reportString>
	
	<!--============= Misc ============-->
	
	<Wear.reportString>Indossando TargetA.</Wear.reportString>
	
	<Strip.reportString>Spogliando TargetA.</Strip.reportString>
	
	<Hunt.reportString>Cacciando TargetA.</Hunt.reportString>
	
	<ManThing.reportString>Azionando macchina.</ManThing.reportString>
	
	<EnterCryptosleepPod.reportString>Entrando in camera d'ibernazione.</EnterCryptosleepPod.reportString>
	
	<!--============ Fire ============-->
	
	<Ignite.reportString>Dando fuoco a TargetA.</Ignite.reportString>
	
	<BeatFire.reportString>Spegnendo il fuoco.</BeatFire.reportString>
	
	<ExtinguishSelf.reportString>Estinguendo l'incendio su di se.</ExtinguishSelf.reportString>
	
	<!--============ Need satisfaction ============-->
	
	<EatFood.reportString>Mangiando TargetA.</EatFood.reportString>
	
	<Sleep.reportString>Dormendo.</Sleep.reportString>
	
	<!--============= Item hauling ===============-->
	
	<HaulToCell.reportString>Spostando TargetA a terra.</HaulToCell.reportString> <!-- NOT TESTED and probably wrong -->
	
	<HaulToContainer.reportString>Spostando TargetA.</HaulToContainer.reportString>
	
	<!--============= Pawn hauling ===============-->
	
	<Rescue.reportString>Salvando TargetA.</Rescue.reportString>
	
	<Capture.reportString>Catturando TargetA.</Capture.reportString>
	
	<Arrest.reportString>Arrestando TargetA.</Arrest.reportString>
	
	<EscortPrisonerToBed.reportString>Scortando prigioniero TargetA.</EscortPrisonerToBed.reportString>
	
	<TakeWoundedPrisonerToBed.reportString>Portando prigioniero TargetA.</TakeWoundedPrisonerToBed.reportString>
	
	<Kidnap.reportString>Rapendo TargetA.</Kidnap.reportString>
	
	
	
	<DeliverFood.reportString>Portando TargetA da mangiare a TargetB.</DeliverFood.reportString>
	
	<FeedPatient.reportString>Facendo mangiare TargetA a TargetB.</FeedPatient.reportString>
	
	<PlaceNoCostFrame.reportString>Costruendo TargetA.</PlaceNoCostFrame.reportString>
	
	<DoBill.reportString>Seguendo il programma a TargetA.</DoBill.reportString>
	
	<Clean.reportString>Pulendo TargetA.</Clean.reportString>
	
	<Research.reportString>Ricercando.</Research.reportString>
	
	<UseCommsConsole.reportString>Usando console di comunicazione.</UseCommsConsole.reportString>
	
	<Mine.reportString>Scavando TargetA.</Mine.reportString>
	
	<Repair.reportString>Riparando TargetA.</Repair.reportString>
	
	<FinishFrame.reportString>Costruendo TargetA.</FinishFrame.reportString>
	
	<Sow.reportString>Piantando TargetA.</Sow.reportString>
	
	<Harvest.reportString>Raccogliendo TargetA.</Harvest.reportString>
	
	<CutPlant.reportString>Tagliando TargetA.</CutPlant.reportString>
	
	<Deconstruct.reportString>Smantellando TargetA.</Deconstruct.reportString>
	
	<PrisonerFriendlyChat.reportString>Parlando col prigioniero TargetA.</PrisonerFriendlyChat.reportString>
	
	<PrisonerBeatingMild.reportString>Picchiando il prigioniero TargetA.</PrisonerBeatingMild.reportString>
	
	<PrisonerBeatingVicious.reportString>Picchiando brutalmente il prigioniero TargetA.</PrisonerBeatingVicious.reportString>
	
	<PrisonerExecution.reportString>Giustiziando il prigioniero TargetA.</PrisonerExecution.reportString>
	
	

</LanguageData>
