<LanguageData>
  
  
  <AutonomousWeapons_Disapproved.label>disapprovato</AutonomousWeapons_Disapproved.label>
  
  <AutonomousWeapons_Disapproved.description>Permettere a una macchina di decidere di uccidere è una cosa brutta.</AutonomousWeapons_Disapproved.description>
  
  <AutonomousWeapons_Disapproved.comps.0.description>Torretta automatizzata nella colonia</AutonomousWeapons_Disapproved.comps.0.description>
  
  
  <AutonomousWeapons_Horrible.label>orribile</AutonomousWeapons_Horrible.label>
  
  <AutonomousWeapons_Horrible.description>Permettere a una macchina di decidere di uccidere è una cosa terribile.</AutonomousWeapons_Horrible.description>
  
  <AutonomousWeapons_Horrible.comps.0.description>Torretta automatizzata nella colonia</AutonomousWeapons_Horrible.comps.0.description>
  
  
  <AutonomousWeapons_Prohibited.label>proibito</AutonomousWeapons_Prohibited.label>
  
  <AutonomousWeapons_Prohibited.description>Permettere a una macchina di decidere di uccidere è una cosa assolutamente disumana.</AutonomousWeapons_Prohibited.description>
  
  <AutonomousWeapons_Prohibited.comps.0.description>Torretta automatizzata nella colonia</AutonomousWeapons_Prohibited.comps.0.description>
  
  <AutonomousWeapons_Prohibited.comps.1.description>Costruire torretta automatizzata</AutonomousWeapons_Prohibited.comps.1.description>
  
</LanguageData>