<?xml version="1.0" encoding="UTF-8"?>
<LanguageData>
  
  <!-- EN: totally abhorrent -->
  <OrganUse_Abhorrent.label>assolutamente ripugnante</OrganUse_Abhorrent.label>
  <!-- EN: Any harvesting, trading, or installing natural organs is an abhorrent evil. -->
  <OrganUse_Abhorrent.description>Qualsiasi asportazione, commercio o impianto di organi naturali è un peccato ripugnante.</OrganUse_Abhorrent.description>
  <!-- EN: Someone harvested an organ -->
  <OrganUse_Abhorrent.comps.2.description>Qualcuno ha asportato un organo</OrganUse_Abhorrent.comps.2.description>
  <!-- EN: Someone traded an organ -->
  <OrganUse_Abhorrent.comps.5.description>Qualcuno ha barattato un organo</OrganUse_Abhorrent.comps.5.description>
  <!-- EN: Someone installed an organ -->
  <OrganUse_Abhorrent.comps.8.description>Qualcuno ha impiantato un organo</OrganUse_Abhorrent.comps.8.description>
  
  <!-- EN: acceptable -->
  <OrganUse_Acceptable.label>accettabile</OrganUse_Acceptable.label>
  <!-- EN: It's okay to harvest, buy, install, or sell organs. -->
  <OrganUse_Acceptable.description>Va bene asportare, comprare, impiantare o vendere organi.</OrganUse_Acceptable.description>
  
  <!-- EN: no harvest or sell -->
  <OrganUse_HorribleNoSell.label>nessuna asportazione o vendita</OrganUse_HorribleNoSell.label>
  <!-- EN: Harvesting organs is a horrible thing. Selling any natural organ is pretty bad too. However, it's okay to buy and install them. -->
  <OrganUse_HorribleNoSell.description>L'asportazione di organi è una cosa orribile. Anche vendere un qualsiasi organo naturale è abbastanza brutto. Tuttavia, va bene comprarli e impiantarli.</OrganUse_HorribleNoSell.description>
  <!-- EN: Someone harvested an organ -->
  <OrganUse_HorribleNoSell.comps.2.description>Qualcuno ha asportato un organo</OrganUse_HorribleNoSell.comps.2.description>
  <!-- EN: Someone sold an organ -->
  <OrganUse_HorribleNoSell.comps.4.description>Qualcuno ha venduto un organo</OrganUse_HorribleNoSell.comps.4.description>
  
  <!-- EN: no harvest -->
  <OrganUse_HorribleSellOK.label>nessuna asportazione</OrganUse_HorribleSellOK.label>
  <!-- EN: Harvesting organs is a horrible thing. However, it's okay to buy, install, or sell them. -->
  <OrganUse_HorribleSellOK.description>Asportare degli organi è una cosa orribile. Tuttavia, va bene comprarli, impiantarli o venderli.</OrganUse_HorribleSellOK.description>
  <!-- EN: Someone harvested an organ -->
  <OrganUse_HorribleSellOK.comps.2.description>Qualcuno ha asportato un organo</OrganUse_HorribleSellOK.comps.2.description>
  
</LanguageData>
