<?xml version="1.0" encoding="UTF-8"?>
<LanguageData>
  
  <!-- EN: relaxed -->
  <ApparelDesired_Soft_Subordinate.label>rilassato</ApparelDesired_Soft_Subordinate.label>
  <!-- EN: {GENDER} members will be pleased when wearing {APPAREL_indefinite}. {GENDER} members will arrive wearing {APPAREL_indefinite} if it doesn't interfere with any other apparel. -->
  <ApparelDesired_Soft_Subordinate.description>I membri di {GENDER} saranno contenti di indossare {APPAREL_indefinite}. I membri {GENDER} arriveranno indossando {APPAREL_indefinite} se non interferisce con altri indumenti.</ApparelDesired_Soft_Subordinate.description>
  <!-- EN: Wearing desired apparel -->
  <ApparelDesired_Soft_Subordinate.comps.1.description>Indossare l'abbigliamento desiderato</ApparelDesired_Soft_Subordinate.comps.1.description>
  
  <!-- EN: strong -->
  <ApparelDesired_Strong_Subordinate.label>forte</ApparelDesired_Strong_Subordinate.label>
  <!-- EN: {GENDER} members will be pleased when wearing {APPAREL_indefinite}. {GENDER} members will arrive wearing {APPAREL_indefinite} unless it interferes with armor. -->
  <ApparelDesired_Strong_Subordinate.description>I membri di {GENDER} saranno contenti di indossare {APPAREL_indefinite}. I membri di {GENDER} arriveranno indossando {APPAREL_indefinite} a meno che non interferisca con l'armatura.</ApparelDesired_Strong_Subordinate.description>
  <!-- EN: Wearing desired apparel -->
  <ApparelDesired_Strong_Subordinate.comps.1.description>Indossare l'abbigliamento desiderato</ApparelDesired_Strong_Subordinate.comps.1.description>
  
</LanguageData>