<?xml version="1.0" encoding="UTF-8"?>
<LanguageData>
  
  <!-- EN: beggars helped -->
  <CharityFulfilled_Beggars.label>mendicanti aiutati</CharityFulfilled_Beggars.label>
  
  <!-- EN: refugees helped -->
  <CharityFulfilled_HospitalityRefugees.label>rifugiati aiutati</CharityFulfilled_HospitalityRefugees.label>
  
  <!-- EN: noble saved -->
  <CharityFulfilled_IntroWimp.label>nobile salvato</CharityFulfilled_IntroWimp.label>
  
  <!-- EN: pod refugee saved -->
  <CharityFulfilled_RefugeePodCrash.label>rifugiato pod salvato</CharityFulfilled_RefugeePodCrash.label>
  
  <!-- EN: crash survivors helped -->
  <CharityFulfilled_ShuttleCrashRescue.label>i sopravvissuti all'incidente sono stati aiutati</CharityFulfilled_ShuttleCrashRescue.label>
  
  <!-- EN: desperate joiner accepted -->
  <CharityFulfilled_ThreatReward_Joiner.label>carpentiere disperato accettato</CharityFulfilled_ThreatReward_Joiner.label>
  
  <!-- EN: wanderer accepted -->
  <CharityFulfilled_WandererJoins.label>vagabondo accettato</CharityFulfilled_WandererJoins.label>
  
  <!-- EN: beggars refused -->
  <CharityRefused_Beggars.label>mendicanti rifiutati</CharityRefused_Beggars.label>
  
  <!-- EN: beggars betrayed -->
  <CharityRefused_Beggars_Betrayed.label>mendicanti traditi</CharityRefused_Beggars_Betrayed.label>
  
  <!-- EN: refugees refused -->
  <CharityRefused_HospitalityRefugees.label>rifugiati rifiutati</CharityRefused_HospitalityRefugees.label>
  
  <!-- EN: wimp refused -->
  <CharityRefused_IntroWimp.label>fifone rifiutato</CharityRefused_IntroWimp.label>
  
  <!-- EN: refugee pod crash refused -->
  <CharityRefused_RefugeePodCrash.label>rifugiato del pod schiantato rifiutato</CharityRefused_RefugeePodCrash.label>
  
  <!-- EN: crash survivors refused -->
  <CharityRefused_ShuttleCrashRescue.label>i sopravvissuti all'incidente sono stati rifiutati</CharityRefused_ShuttleCrashRescue.label>
  
  <!-- EN: joiner refused -->
  <CharityRefused_ThreatReward_Joiner.label>carpentiere rifiutato</CharityRefused_ThreatReward_Joiner.label>
  
  <!-- EN: wanderer refused -->
  <CharityRefused_WandererJoins.label>vagabondo rifiutato</CharityRefused_WandererJoins.label>
  
</LanguageData>
