<LanguageData>
  
  
  <AteMeat_Abhorrent.stages.ate_meat.label>TODO</AteMeat_Abhorrent.stages.ate_meat.label>
  
  <AteMeat_Abhorrent.stages.ate_meat.description>TODO</AteMeat_Abhorrent.stages.ate_meat.description>
  
  
  <AteMeat_Disapproved.stages.ate_meat.label>TODO</AteMeat_Disapproved.stages.ate_meat.label>
  
  <AteMeat_Disapproved.stages.ate_meat.description>TODO</AteMeat_Disapproved.stages.ate_meat.description>
  
  
  <AteMeat_Horrible.stages.ate_meat.label>TODO</AteMeat_Horrible.stages.ate_meat.label>
  
  <AteMeat_Horrible.stages.ate_meat.description>TODO</AteMeat_Horrible.stages.ate_meat.description>
  
  
  <AteMeat_Know_Abhorrent.stages.ate_meat.label>TODO</AteMeat_Know_Abhorrent.stages.ate_meat.label>
  
  
  <AteMeat_Know_Disapproved.stages.ate_meat.label>TODO</AteMeat_Know_Disapproved.stages.ate_meat.label>
  
  
  <AteMeat_Know_Horrible.stages.ate_meat.label>TODO</AteMeat_Know_Horrible.stages.ate_meat.label>
  
  
  <AteNonMeat_Abhorrent.stages.ate_vegetarian.label>TODO</AteNonMeat_Abhorrent.stages.ate_vegetarian.label>
  
  <AteNonMeat_Abhorrent.stages.ate_vegetarian.description>TODO</AteNonMeat_Abhorrent.stages.ate_vegetarian.description>
  
  
  <AteNonMeat_Disapproved.stages.ate_vegetarian.label>TODO</AteNonMeat_Disapproved.stages.ate_vegetarian.label>
  
  <AteNonMeat_Disapproved.stages.ate_vegetarian.description>TODO</AteNonMeat_Disapproved.stages.ate_vegetarian.description>
  
  
  <AteNonMeat_Horrible.stages.ate_vegetarian.label>TODO</AteNonMeat_Horrible.stages.ate_vegetarian.label>
  
  <AteNonMeat_Horrible.stages.ate_vegetarian.description>TODO</AteNonMeat_Horrible.stages.ate_vegetarian.description>
  
  
  <AteNonMeat_Know_Abhorrent.stages.ate_vegetarian.label>TODO</AteNonMeat_Know_Abhorrent.stages.ate_vegetarian.label>
  
  
  <AteNonMeat_Know_Disapproved.stages.ate_vegetarian.label>TODO</AteNonMeat_Know_Disapproved.stages.ate_vegetarian.label>
  
  
  <AteNonMeat_Know_Horrible.stages.ate_vegetarian.label>TODO</AteNonMeat_Know_Horrible.stages.ate_vegetarian.label>
  
</LanguageData>