<?xml version="1.0" encoding="UTF-8"?>
<LanguageData>
  
  <!-- EN:
    <li>r_ritualName->[ritNoun] of [keyDeity]</li>
    <li>r_ritualName->[ritNoun] of [chosenTheme]</li>
    <li>r_ritualName->[ritNoun] of [memeConcept]</li>
    <li>r_ritualName->[memeAdjective] [ritNoun]</li>
    <li>ritNoun->mutilation</li>
    <li>ritNoun->cutting</li>
    <li>ritNoun->slicing</li>
    <li>ritNoun->peeling</li>
    <li>ritNoun->bladerip</li>
    <li>ritNoun->ripping</li>
    <li>ritNoun->mangling</li>
    <li>ritNoun->fleshcarving</li>
    <li>ritNoun->gashing</li>
    <li>ritNoun->rend</li>
  -->
  <NamerRitualMutilation.rulePack.rulesStrings>
    <li>r_ritualName->[ritNoun] di [keyDeity]</li>
    <li>r_ritualName->[ritNoun] di [chosenTheme]</li>
    <li>r_ritualName->[ritNoun] di [memeConcept]</li>
    <li>r_ritualName->[ritNoun_M] [memeAdjective]</li>
    <li>r_ritualName->[ritNoun_F] [memeAdjectiveFem]</li>
    <li>ritNoun->[ritNoun_M]</li>
    <li>ritNoun->[ritNoun_F]</li>
    <li>ritNoun_M->taglio</li>
    <li>ritNoun_M->strappo di lama</li>
    <li>ritNoun_M->strappo</li>
    <li>ritNoun_M->sfregio</li>
    <li>ritNoun_F->mutilazione</li>
    <li>ritNoun_F->affettatura</li>
    <li>ritNoun_F->scorticatura</li>
    <li>ritNoun_F->deturpazione</li>
    <li>ritNoun_F->scultura di carne</li>
    <li>ritNoun_F->lacerazione</li>
  </NamerRitualMutilation.rulePack.rulesStrings>
  
</LanguageData>