<?xml version="1.0" encoding="UTF-8"?>
<LanguageData>
  
  <!-- EN: journey offer -->
  <GiveQuest_EndGame_ShipEscape.label>offerta di viaggio</GiveQuest_EndGame_ShipEscape.label>
  <!-- EN: Journey offer -->
  <GiveQuest_EndGame_ShipEscape.letterLabel>Offerta di viaggio</GiveQuest_EndGame_ShipEscape.letterLabel>
  
  <!-- EN: quest -->
  <GiveQuest_Random.label>Missione</GiveQuest_Random.label>
  <!-- EN: Quest available -->
  <GiveQuest_Random.letterLabel>Missione disponibile</GiveQuest_Random.letterLabel>
  
  <!-- UNUSED -->
  <Quest_BanditCamp.label>missione campo dei banditi</Quest_BanditCamp.label>
  <Quest_BanditCamp.letterLabel>Missione campo dei banditi</Quest_BanditCamp.letterLabel>
  <Quest_BanditCamp.letterText>{0}, {1} di {2} ci hanno inviato un messaggio.\n\nApparentemente, dei banditi accampati nelle vicinanze stanno assaltando le loro carovane. Ci hanno chiesto di distruggerlo, il che vuol dire eliminare tutti i nemici e le difese.\n\n{0} dice che {5}.\n\nSe avremo successo, le nostre relazioni miglioreranno e ci manderanno questa ricompensa dal valore di {6}:\n\n{3}\n\nSe non distruggeremo il campo in {4} giorni, lo faranno loro stessi.</Quest_BanditCamp.letterText>
  
  <!-- UNUSED -->
  <Quest_DownedRefugee.label>missione rifugiato inerme</Quest_DownedRefugee.label>
  <Quest_DownedRefugee.letterLabel>Missione rifugiato inerme</Quest_DownedRefugee.letterLabel>
  <Quest_DownedRefugee.letterText>{PAWN_nameDef} ti ha contattato e chiede aiuto. {PAWN_pronoun} è ferit{PAWN_gender ? o:a} ed incapace di muoversi. Senza il tuo aiuto {PAWN_pronoun} morirà in {0} giorni.\n\n{PAWN_nameDef} è un {2} di {1} anni. {PAWN_pronoun} ti promette di unirsi a te se {PAWN_gender ? lo:la} salverai.\n\n{PAWN_nameDef} dice che {3}.</Quest_DownedRefugee.letterText>
  
  <!-- UNUSED -->
  <Quest_ItemStash.label>missione rifornimenti</Quest_ItemStash.label>
  <Quest_ItemStash.letterLabel>Missione rifornimenti</Quest_ItemStash.letterLabel>
  <Quest_ItemStash.letterText>{0}, {1} di {2} ci hanno informato di un carico di oggetti del valore di {6} non lontano da noi. Il carico consiste in:\n\n{3}\n\nSfortunatamente non durerà a lungo: altri prenderanno la merce in {4} giorni, se non lo faremo noi.\n\nAttento: gli oggetti di valore tendono ad attirare i pericoli. {0} dice che {5}.</Quest_ItemStash.letterText>
  
  <!-- UNUSED -->
  <Quest_ItemStashAICore.label>missione rifornimenti (nucleo IA)</Quest_ItemStashAICore.label>
  <Quest_ItemStashAICore.letterLabel>Missione rifornimenti</Quest_ItemStashAICore.letterLabel>
  <Quest_ItemStashAICore.letterText>{0}, {1} di {2} ci hanno informato di un carico di oggetti del valore di {6} non lontano da noi. Il carico consiste in:\n\n{3}\n\nSfortunatamente non durerà a lungo: altri prenderanno la merce in {4} giorni, se non lo faremo noi.\n\nAttento: gli oggetti di valore tendono ad attirare i pericoli. {0} dice che {5}.</Quest_ItemStashAICore.letterText>
  
  <!-- UNUSED -->
  <Quest_JourneyOffer.label>missione astronave di salvataggio</Quest_JourneyOffer.label>
  
  <!-- UNUSED -->
  <Quest_PeaceTalks.label>missione trattative di pace</Quest_PeaceTalks.label>
  <Quest_PeaceTalks.letterLabel>Missione trattative di pace</Quest_PeaceTalks.letterLabel>
  <Quest_PeaceTalks.letterText>{PAWN_nameDef}, {0} di {1}, ci ha inviato un messaggio. {PAWN_pronoun} vuole parlare con noi in un luogo vicino.\n\nPotrebbe essere un'ottima opportunità per migliorare le relazioni con la loro fazione e ricevere offerte, ma attento: uno scarso negoziatore può provocare più danni che altro e può anche farli arrabbiare.\n\nLa proposta terminerà dopo {2} giorni.</Quest_PeaceTalks.letterText>
  
  <!-- UNUSED -->
  <Quest_PrisonerRescue.label>missione salvataggio prigioniero</Quest_PrisonerRescue.label>
  <Quest_PrisonerRescue.letterLabel>Missione salvataggio prigioniero</Quest_PrisonerRescue.letterLabel>
  <Quest_PrisonerRescue.letterText>Un prigioniero tenuto da {0} è riuscito a rubare una radio ed a chiamarti!\n\n{PAWN_nameDef} è tenut{PAWN_gender ? o:a} sotto scorta armata in un campo vicino. Salval{PAWN_gender ? o:a} e {PAWN_pronoun} si unirà alla tua colonia. {PAWN_pronoun} è un {2} di {1} anni. {PAWN_pronoun} dice che {3}.</Quest_PrisonerRescue.letterText>
  
  <!-- UNUSED -->
  <Quest_TradeRequest.label>richiesta commerciale</Quest_TradeRequest.label>
  
</LanguageData>