<?xml version="1.0" encoding="UTF-8"?>
<LanguageData>
  
  <!-- EN: make granite blocks -->
  <Make_StoneBlocksGranite.label>Intagliare blocchi di granito</Make_StoneBlocksGranite.label>
  <!-- EN: Cuts granite chunks into usable blocks. -->
  <Make_StoneBlocksGranite.description>Intagliare dei pezzi di granito in blocchi utilizzabili.</Make_StoneBlocksGranite.description>
  <!-- EN: Cutting stone blocks from chunk. -->
  <Make_StoneBlocksGranite.jobString>Intaglia dei blocchi di granito.</Make_StoneBlocksGranite.jobString>
  
  <!-- EN: make limestone blocks -->
  <Make_StoneBlocksLimestone.label>Intagliare blocchi di calcare</Make_StoneBlocksLimestone.label>
  <!-- EN: Cuts limestone chunks into usable blocks. -->
  <Make_StoneBlocksLimestone.description>Intagliare dei pezzi di calcare in blocchi utilizzabili.</Make_StoneBlocksLimestone.description>
  <!-- EN: Cutting stone blocks from chunk. -->
  <Make_StoneBlocksLimestone.jobString>Intaglia dei blocchi di calcare.</Make_StoneBlocksLimestone.jobString>
  
  <!-- EN: make marble blocks -->
  <Make_StoneBlocksMarble.label>Intagliare blocchi di marmo</Make_StoneBlocksMarble.label>
  <!-- EN: Cuts marble chunks into usable blocks. -->
  <Make_StoneBlocksMarble.description>Intagliare dei pezzi di marmo in blocchi utilizzabili.</Make_StoneBlocksMarble.description>
  <!-- EN: Cutting stone blocks from chunk. -->
  <Make_StoneBlocksMarble.jobString>Intaglia dei blocchi di marmo.</Make_StoneBlocksMarble.jobString>
  
  <!-- EN: make sandstone blocks -->
  <Make_StoneBlocksSandstone.label>Intagliare blocchi di arenaria</Make_StoneBlocksSandstone.label>
  <!-- EN: Cuts sandstone chunks into usable blocks. -->
  <Make_StoneBlocksSandstone.description>Intagliare dei pezzi di arenaria in blocchi utilizzabili.</Make_StoneBlocksSandstone.description>
  <!-- EN: Cutting stone blocks from chunk. -->
  <Make_StoneBlocksSandstone.jobString>Intaglia dei blocchi di arenaria.</Make_StoneBlocksSandstone.jobString>
  
  <!-- EN: make slate blocks -->
  <Make_StoneBlocksSlate.label>Intagliare blocchi di ardesia</Make_StoneBlocksSlate.label>
  <!-- EN: Cuts slate chunks into usable blocks. -->
  <Make_StoneBlocksSlate.description>Intagliare dei pezzi di ardesia in blocchi utilizzabili.</Make_StoneBlocksSlate.description>
  <!-- EN: Cutting stone blocks from chunk. -->
  <Make_StoneBlocksSlate.jobString>Intaglia dei blocchi di ardesia.</Make_StoneBlocksSlate.jobString>
  
</LanguageData>