<?xml version="1.0" encoding="UTF-8"?>
<LanguageData>
  
  <!-- EN: kid outfit stand -->
  <Building_KidOutfitStand.label>appendiabiti per bambini</Building_KidOutfitStand.label>
  <!-- EN: A small display that showcases a single outfit for a child. Saves space and can be used to quickly change clothing. -->
  <Building_KidOutfitStand.description>Un piccolo espositore che mostra un singolo abito per bambino. Fa risparmiare spazio e può essere usato per cambiare rapidamente i vestiti.</Building_KidOutfitStand.description>
  
  <!-- EN: outfit stand -->
  <Building_OutfitStand.label>appendiabiti</Building_OutfitStand.label>
  <!-- EN: A small display that showcases a single outfit. Saves space and can be used to quickly change clothing. -->
  <Building_OutfitStand.description>Un piccolo espositore che mostra un singolo abito. Fa risparmiare spazio e può essere usato per cambiare rapidamente i vestiti.</Building_OutfitStand.description>
  
</LanguageData>