<?xml version="1.0" encoding="UTF-8"?>
<LanguageData>
  
  <!-- EN: unique greatbow -->
  <Bow_Great_Unique.label>arco lungo unico</Bow_Great_Unique.label>
  <!-- EN: A greatbow with customized parts. -->
  <Bow_Great_Unique.description>Un arco lungo con parti personalizzate.</Bow_Great_Unique.description>
  <!-- EN: charge -->
  <Bow_Great_Unique.comps.CompEquippableAbilityReloadable.chargeNoun>carica</Bow_Great_Unique.comps.CompEquippableAbilityReloadable.chargeNoun>
  <!-- EN: on cooldown -->
  <Bow_Great_Unique.comps.CompEquippableAbilityReloadable.cooldownGerund>in ricarica</Bow_Great_Unique.comps.CompEquippableAbilityReloadable.cooldownGerund>
  <!-- EN: greatbow -->
  <Bow_Great_Unique.comps.CompUniqueWeapon.namerLabels.0>arco lungo</Bow_Great_Unique.comps.CompUniqueWeapon.namerLabels.0>
  <!-- EN: bow -->
  <Bow_Great_Unique.comps.CompUniqueWeapon.namerLabels.1>arco</Bow_Great_Unique.comps.CompUniqueWeapon.namerLabels.1>
  <!-- EN: limb -->
  <Bow_Great_Unique.tools.limb.label>braccio</Bow_Great_Unique.tools.limb.label>
  <!-- EN: unique greatbow -->
  <Bow_Great_Unique.verbs.Verb_Shoot.label>arco lungo unico</Bow_Great_Unique.verbs.Verb_Shoot.label>
  
  <!-- EN: unique assault rifle -->
  <Gun_AssaultRifle_Unique.label>fucile d'assalto unico</Gun_AssaultRifle_Unique.label>
  <!-- EN: An assault rifle with customized parts. -->
  <Gun_AssaultRifle_Unique.description>Un fucile d'assalto con parti personalizzate.</Gun_AssaultRifle_Unique.description>
  <!-- EN: charge -->
  <Gun_AssaultRifle_Unique.comps.CompEquippableAbilityReloadable.chargeNoun>carica</Gun_AssaultRifle_Unique.comps.CompEquippableAbilityReloadable.chargeNoun>
  <!-- EN: on cooldown -->
  <Gun_AssaultRifle_Unique.comps.CompEquippableAbilityReloadable.cooldownGerund>in ricarica</Gun_AssaultRifle_Unique.comps.CompEquippableAbilityReloadable.cooldownGerund>
  <!-- EN: assault rifle -->
  <Gun_AssaultRifle_Unique.comps.CompUniqueWeapon.namerLabels.0>fucile d'assalto</Gun_AssaultRifle_Unique.comps.CompUniqueWeapon.namerLabels.0>
  <!-- EN: carbine -->
  <Gun_AssaultRifle_Unique.comps.CompUniqueWeapon.namerLabels.1>carabina</Gun_AssaultRifle_Unique.comps.CompUniqueWeapon.namerLabels.1>
  <!-- EN: battle rifle -->
  <Gun_AssaultRifle_Unique.comps.CompUniqueWeapon.namerLabels.2>fucile da battaglia</Gun_AssaultRifle_Unique.comps.CompUniqueWeapon.namerLabels.2>
  <!-- EN: war rifle -->
  <Gun_AssaultRifle_Unique.comps.CompUniqueWeapon.namerLabels.3>fucile da guerra</Gun_AssaultRifle_Unique.comps.CompUniqueWeapon.namerLabels.3>
  <!-- EN: wargun -->
  <Gun_AssaultRifle_Unique.comps.CompUniqueWeapon.namerLabels.4>arma da guerra</Gun_AssaultRifle_Unique.comps.CompUniqueWeapon.namerLabels.4>
  <!-- EN: fusil -->
  <Gun_AssaultRifle_Unique.comps.CompUniqueWeapon.namerLabels.5>fucile</Gun_AssaultRifle_Unique.comps.CompUniqueWeapon.namerLabels.5>
  <!-- EN: stock -->
  <Gun_AssaultRifle_Unique.tools.stock.label>calcio</Gun_AssaultRifle_Unique.tools.stock.label>
  <!-- EN: barrel -->
  <Gun_AssaultRifle_Unique.tools.barrel.label>canna</Gun_AssaultRifle_Unique.tools.barrel.label>
  <!-- EN: unique assault rifle -->
  <Gun_AssaultRifle_Unique.verbs.Verb_Shoot.label>fucile d'assalto unico</Gun_AssaultRifle_Unique.verbs.Verb_Shoot.label>
  
  <!-- EN: unique beam repeater -->
  <Gun_BeamRepeater_Unique.label>ripetitore a fascio unico</Gun_BeamRepeater_Unique.label>
  <!-- EN: A beam repeater with customized parts. -->
  <Gun_BeamRepeater_Unique.description>Un ripetitore a fascio con parti personalizzate.</Gun_BeamRepeater_Unique.description>
  <!-- EN: charge -->
  <Gun_BeamRepeater_Unique.comps.CompEquippableAbilityReloadable.chargeNoun>carica</Gun_BeamRepeater_Unique.comps.CompEquippableAbilityReloadable.chargeNoun>
  <!-- EN: on cooldown -->
  <Gun_BeamRepeater_Unique.comps.CompEquippableAbilityReloadable.cooldownGerund>in ricarica</Gun_BeamRepeater_Unique.comps.CompEquippableAbilityReloadable.cooldownGerund>
  <!-- EN: repeater -->
  <Gun_BeamRepeater_Unique.comps.CompUniqueWeapon.namerLabels.0>ripetitore</Gun_BeamRepeater_Unique.comps.CompUniqueWeapon.namerLabels.0>
  <!-- EN: beam repeater -->
  <Gun_BeamRepeater_Unique.comps.CompUniqueWeapon.namerLabels.1>ripetitore a fascio</Gun_BeamRepeater_Unique.comps.CompUniqueWeapon.namerLabels.1>
  <!-- EN: beamgun -->
  <Gun_BeamRepeater_Unique.comps.CompUniqueWeapon.namerLabels.2>cannone a fascio</Gun_BeamRepeater_Unique.comps.CompUniqueWeapon.namerLabels.2>
  <!-- EN: barrels -->
  <Gun_BeamRepeater_Unique.tools.barrels.label>canne</Gun_BeamRepeater_Unique.tools.barrels.label>
  <!-- EN: unique beam repeater -->
  <Gun_BeamRepeater_Unique.verbs.Verb_Shoot.label>ripetitore a fascio unico</Gun_BeamRepeater_Unique.verbs.Verb_Shoot.label>
  
  <!-- EN: unique bolt-action rifle -->
  <Gun_BoltActionRifle_Unique.label>fucile a otturatore scorrevole unico</Gun_BoltActionRifle_Unique.label>
  <!-- EN: A bolt-action rifle with customized parts. -->
  <Gun_BoltActionRifle_Unique.description>Un fucile a otturatore scorrevole con parti personalizzate.</Gun_BoltActionRifle_Unique.description>
  <!-- EN: charge -->
  <Gun_BoltActionRifle_Unique.comps.CompEquippableAbilityReloadable.chargeNoun>carica</Gun_BoltActionRifle_Unique.comps.CompEquippableAbilityReloadable.chargeNoun>
  <!-- EN: on cooldown -->
  <Gun_BoltActionRifle_Unique.comps.CompEquippableAbilityReloadable.cooldownGerund>in ricarica</Gun_BoltActionRifle_Unique.comps.CompEquippableAbilityReloadable.cooldownGerund>
  <!-- EN: bolt-action rifle -->
  <Gun_BoltActionRifle_Unique.comps.CompUniqueWeapon.namerLabels.0>fucile a otturatore girevole-scorrevole</Gun_BoltActionRifle_Unique.comps.CompUniqueWeapon.namerLabels.0>
  <!-- EN: thumper -->
  <Gun_BoltActionRifle_Unique.comps.CompUniqueWeapon.namerLabels.1>martellatore</Gun_BoltActionRifle_Unique.comps.CompUniqueWeapon.namerLabels.1>
  <!-- EN: bolt-gun -->
  <Gun_BoltActionRifle_Unique.comps.CompUniqueWeapon.namerLabels.2>arma a otturatore</Gun_BoltActionRifle_Unique.comps.CompUniqueWeapon.namerLabels.2>
  <!-- EN: rifle -->
  <Gun_BoltActionRifle_Unique.comps.CompUniqueWeapon.namerLabels.3>fucile</Gun_BoltActionRifle_Unique.comps.CompUniqueWeapon.namerLabels.3>
  <!-- EN: longshot -->
  <Gun_BoltActionRifle_Unique.comps.CompUniqueWeapon.namerLabels.4>colpo lungo</Gun_BoltActionRifle_Unique.comps.CompUniqueWeapon.namerLabels.4>
  <!-- EN: longshooter -->
  <Gun_BoltActionRifle_Unique.comps.CompUniqueWeapon.namerLabels.5>tiratore a lunga distanza</Gun_BoltActionRifle_Unique.comps.CompUniqueWeapon.namerLabels.5>
  <!-- EN: stock -->
  <Gun_BoltActionRifle_Unique.tools.stock.label>calcio</Gun_BoltActionRifle_Unique.tools.stock.label>
  <!-- EN: barrel -->
  <Gun_BoltActionRifle_Unique.tools.barrel.label>canna</Gun_BoltActionRifle_Unique.tools.barrel.label>
  <!-- EN: unique bolt-action rifle -->
  <Gun_BoltActionRifle_Unique.verbs.Verb_Shoot.label>fucile a otturatore scorrevole unico</Gun_BoltActionRifle_Unique.verbs.Verb_Shoot.label>
  
  <!-- EN: unique chain shotgun -->
  <Gun_ChainShotgun_Unique.label>fucile a pompa automatico unico</Gun_ChainShotgun_Unique.label>
  <!-- EN: A chain shotgun with customized parts. -->
  <Gun_ChainShotgun_Unique.description>Un fucile a pompa automatico con parti personalizzate.</Gun_ChainShotgun_Unique.description>
  <!-- EN: charge -->
  <Gun_ChainShotgun_Unique.comps.CompEquippableAbilityReloadable.chargeNoun>carica</Gun_ChainShotgun_Unique.comps.CompEquippableAbilityReloadable.chargeNoun>
  <!-- EN: on cooldown -->
  <Gun_ChainShotgun_Unique.comps.CompEquippableAbilityReloadable.cooldownGerund>in ricarica</Gun_ChainShotgun_Unique.comps.CompEquippableAbilityReloadable.cooldownGerund>
  <!-- EN: chain shotgun -->
  <Gun_ChainShotgun_Unique.comps.CompUniqueWeapon.namerLabels.0>fucile a pompa automatico</Gun_ChainShotgun_Unique.comps.CompUniqueWeapon.namerLabels.0>
  <!-- EN: shotgun -->
  <Gun_ChainShotgun_Unique.comps.CompUniqueWeapon.namerLabels.1>fucile a pompa</Gun_ChainShotgun_Unique.comps.CompUniqueWeapon.namerLabels.1>
  <!-- EN: chainshot -->
  <Gun_ChainShotgun_Unique.comps.CompUniqueWeapon.namerLabels.2>colpo a catena</Gun_ChainShotgun_Unique.comps.CompUniqueWeapon.namerLabels.2>
  <!-- EN: blaster -->
  <Gun_ChainShotgun_Unique.comps.CompUniqueWeapon.namerLabels.3>blaster</Gun_ChainShotgun_Unique.comps.CompUniqueWeapon.namerLabels.3>
  <!-- EN: blaststick -->
  <Gun_ChainShotgun_Unique.comps.CompUniqueWeapon.namerLabels.4>bastone esplosivo</Gun_ChainShotgun_Unique.comps.CompUniqueWeapon.namerLabels.4>
  <!-- EN: sweeper -->
  <Gun_ChainShotgun_Unique.comps.CompUniqueWeapon.namerLabels.5>spazzino</Gun_ChainShotgun_Unique.comps.CompUniqueWeapon.namerLabels.5>
  <!-- EN: gutspewer -->
  <Gun_ChainShotgun_Unique.comps.CompUniqueWeapon.namerLabels.6>sventratore</Gun_ChainShotgun_Unique.comps.CompUniqueWeapon.namerLabels.6>
  <!-- EN: stock -->
  <Gun_ChainShotgun_Unique.tools.stock.label>calcio</Gun_ChainShotgun_Unique.tools.stock.label>
  <!-- EN: barrel -->
  <Gun_ChainShotgun_Unique.tools.barrel.label>canna</Gun_ChainShotgun_Unique.tools.barrel.label>
  <!-- EN: unique chain shotgun -->
  <Gun_ChainShotgun_Unique.verbs.Verb_Shoot.label>fucile a pompa automatico unico</Gun_ChainShotgun_Unique.verbs.Verb_Shoot.label>
  
  <!-- EN: unique charge lance -->
  <Gun_ChargeLance_Unique.label>lancia a carica unica</Gun_ChargeLance_Unique.label>
  <!-- EN: A charge lance with customized parts. -->
  <Gun_ChargeLance_Unique.description>Una lancia a carica con parti personalizzate.</Gun_ChargeLance_Unique.description>
  <!-- EN: charge -->
  <Gun_ChargeLance_Unique.comps.CompEquippableAbilityReloadable.chargeNoun>carica</Gun_ChargeLance_Unique.comps.CompEquippableAbilityReloadable.chargeNoun>
  <!-- EN: on cooldown -->
  <Gun_ChargeLance_Unique.comps.CompEquippableAbilityReloadable.cooldownGerund>in ricarica</Gun_ChargeLance_Unique.comps.CompEquippableAbilityReloadable.cooldownGerund>
  <!-- EN: charge lance -->
  <Gun_ChargeLance_Unique.comps.CompUniqueWeapon.namerLabels.0>lancia a carica</Gun_ChargeLance_Unique.comps.CompUniqueWeapon.namerLabels.0>
  <!-- EN: barrel -->
  <Gun_ChargeLance_Unique.tools.barrel.label>canna</Gun_ChargeLance_Unique.tools.barrel.label>
  <!-- EN: unique charge lance -->
  <Gun_ChargeLance_Unique.verbs.Verb_Shoot.label>lancia a carica unica</Gun_ChargeLance_Unique.verbs.Verb_Shoot.label>
  
  <!-- EN: unique charge rifle -->
  <Gun_ChargeRifle_Unique.label>fucile a carica unico</Gun_ChargeRifle_Unique.label>
  <!-- EN: A charge rifle with customized parts. -->
  <Gun_ChargeRifle_Unique.description>Un fucile a carica con parti personalizzate.</Gun_ChargeRifle_Unique.description>
  <!-- EN: charge -->
  <Gun_ChargeRifle_Unique.comps.CompEquippableAbilityReloadable.chargeNoun>carica</Gun_ChargeRifle_Unique.comps.CompEquippableAbilityReloadable.chargeNoun>
  <!-- EN: on cooldown -->
  <Gun_ChargeRifle_Unique.comps.CompEquippableAbilityReloadable.cooldownGerund>in ricarica</Gun_ChargeRifle_Unique.comps.CompEquippableAbilityReloadable.cooldownGerund>
  <!-- EN: charge rifle -->
  <Gun_ChargeRifle_Unique.comps.CompUniqueWeapon.namerLabels.0>fucile a carica</Gun_ChargeRifle_Unique.comps.CompUniqueWeapon.namerLabels.0>
  <!-- EN: stock -->
  <Gun_ChargeRifle_Unique.tools.stock.label>calcio</Gun_ChargeRifle_Unique.tools.stock.label>
  <!-- EN: barrel -->
  <Gun_ChargeRifle_Unique.tools.barrel.label>canna</Gun_ChargeRifle_Unique.tools.barrel.label>
  <!-- EN: unique charge rifle -->
  <Gun_ChargeRifle_Unique.verbs.Verb_Shoot.label>fucile a carica unico</Gun_ChargeRifle_Unique.verbs.Verb_Shoot.label>
  
  <!-- EN: unique heavy SMG -->
  <Gun_HeavySMG_Unique.label>mitra pesante unico</Gun_HeavySMG_Unique.label>
  <!-- EN: A heavy SMG with customized parts. -->
  <Gun_HeavySMG_Unique.description>Un mitra pesante con parti personalizzate.</Gun_HeavySMG_Unique.description>
  <!-- EN: charge -->
  <Gun_HeavySMG_Unique.comps.CompEquippableAbilityReloadable.chargeNoun>carica</Gun_HeavySMG_Unique.comps.CompEquippableAbilityReloadable.chargeNoun>
  <!-- EN: on cooldown -->
  <Gun_HeavySMG_Unique.comps.CompEquippableAbilityReloadable.cooldownGerund>in ricarica</Gun_HeavySMG_Unique.comps.CompEquippableAbilityReloadable.cooldownGerund>
  <!-- EN: heavy SMG -->
  <Gun_HeavySMG_Unique.comps.CompUniqueWeapon.namerLabels.0>mitra pesante</Gun_HeavySMG_Unique.comps.CompUniqueWeapon.namerLabels.0>
  <!-- EN: SMG -->
  <Gun_HeavySMG_Unique.comps.CompUniqueWeapon.namerLabels.1>mitra</Gun_HeavySMG_Unique.comps.CompUniqueWeapon.namerLabels.1>
  <!-- EN: chugger -->
  <Gun_HeavySMG_Unique.comps.CompUniqueWeapon.namerLabels.2>rafficatore</Gun_HeavySMG_Unique.comps.CompUniqueWeapon.namerLabels.2>
  <!-- EN: grip -->
  <Gun_HeavySMG_Unique.tools.grip.label>impugnatura</Gun_HeavySMG_Unique.tools.grip.label>
  <!-- EN: barrel -->
  <Gun_HeavySMG_Unique.tools.barrel.label>canna</Gun_HeavySMG_Unique.tools.barrel.label>
  <!-- EN: unique heavy SMG -->
  <Gun_HeavySMG_Unique.verbs.Verb_Shoot.label>mitra pesante unico</Gun_HeavySMG_Unique.verbs.Verb_Shoot.label>
  
  <!-- EN: unique hellcat rifle -->
  <Gun_HellcatRifle_Unique.label>fucile infernale unico</Gun_HellcatRifle_Unique.label>
  <!-- EN: A hellcat rifle with customized parts. -->
  <Gun_HellcatRifle_Unique.description>Un fucile infernale con parti personalizzate.</Gun_HellcatRifle_Unique.description>
  <!-- EN: burner charge -->
  <Gun_HellcatRifle_Unique.comps.CompEquippableAbilityReloadable.chargeNoun>carica incendiaria</Gun_HellcatRifle_Unique.comps.CompEquippableAbilityReloadable.chargeNoun>
  <!-- EN: on cooldown -->
  <Gun_HellcatRifle_Unique.comps.CompEquippableAbilityReloadable.cooldownGerund>in ricarica</Gun_HellcatRifle_Unique.comps.CompEquippableAbilityReloadable.cooldownGerund>
  <!-- EN: hellcat rifle -->
  <Gun_HellcatRifle_Unique.comps.CompUniqueWeapon.namerLabels.0>fucile infernale</Gun_HellcatRifle_Unique.comps.CompUniqueWeapon.namerLabels.0>
  <!-- EN: hellcat -->
  <Gun_HellcatRifle_Unique.comps.CompUniqueWeapon.namerLabels.1>hellcat</Gun_HellcatRifle_Unique.comps.CompUniqueWeapon.namerLabels.1>
  <!-- EN: flamer -->
  <Gun_HellcatRifle_Unique.comps.CompUniqueWeapon.namerLabels.2>lanciafiamme</Gun_HellcatRifle_Unique.comps.CompUniqueWeapon.namerLabels.2>
  <!-- EN: flamegun -->
  <Gun_HellcatRifle_Unique.comps.CompUniqueWeapon.namerLabels.3>cannone incendiario</Gun_HellcatRifle_Unique.comps.CompUniqueWeapon.namerLabels.3>
  <!-- EN: burner -->
  <Gun_HellcatRifle_Unique.comps.CompUniqueWeapon.namerLabels.4>bruciatore</Gun_HellcatRifle_Unique.comps.CompUniqueWeapon.namerLabels.4>
  <!-- EN: burngun -->
  <Gun_HellcatRifle_Unique.comps.CompUniqueWeapon.namerLabels.5>cannone bruciatore</Gun_HellcatRifle_Unique.comps.CompUniqueWeapon.namerLabels.5>
  <!-- EN: stock -->
  <Gun_HellcatRifle_Unique.tools.stock.label>calcio</Gun_HellcatRifle_Unique.tools.stock.label>
  <!-- EN: barrel -->
  <Gun_HellcatRifle_Unique.tools.barrel.label>canna</Gun_HellcatRifle_Unique.tools.barrel.label>
  <!-- EN: unique hellcat rifle -->
  <Gun_HellcatRifle_Unique.verbs.Verb_Shoot.label>fucile infernale unico</Gun_HellcatRifle_Unique.verbs.Verb_Shoot.label>
  
  <!-- EN: unique LMG -->
  <Gun_LMG_Unique.label>mitragliatrice leggera unica</Gun_LMG_Unique.label>
  <!-- EN: An LMG with customized parts. -->
  <Gun_LMG_Unique.description>Una mitragliatrice leggera con parti personalizzate.</Gun_LMG_Unique.description>
  <!-- EN: charge -->
  <Gun_LMG_Unique.comps.CompEquippableAbilityReloadable.chargeNoun>carica</Gun_LMG_Unique.comps.CompEquippableAbilityReloadable.chargeNoun>
  <!-- EN: on cooldown -->
  <Gun_LMG_Unique.comps.CompEquippableAbilityReloadable.cooldownGerund>in ricarica</Gun_LMG_Unique.comps.CompEquippableAbilityReloadable.cooldownGerund>
  <!-- EN: LMG -->
  <Gun_LMG_Unique.comps.CompUniqueWeapon.namerLabels.0>LMG</Gun_LMG_Unique.comps.CompUniqueWeapon.namerLabels.0>
  <!-- EN: machine gun -->
  <Gun_LMG_Unique.comps.CompUniqueWeapon.namerLabels.1>mitragliatrice</Gun_LMG_Unique.comps.CompUniqueWeapon.namerLabels.1>
  <!-- EN: light machine gun -->
  <Gun_LMG_Unique.comps.CompUniqueWeapon.namerLabels.2>mitragliatrice leggera</Gun_LMG_Unique.comps.CompUniqueWeapon.namerLabels.2>
  <!-- EN: stock -->
  <Gun_LMG_Unique.tools.stock.label>calcio</Gun_LMG_Unique.tools.stock.label>
  <!-- EN: barrel -->
  <Gun_LMG_Unique.tools.barrel.label>canna</Gun_LMG_Unique.tools.barrel.label>
  <!-- EN: unique LMG -->
  <Gun_LMG_Unique.verbs.Verb_Shoot.label>mitragliatrice leggera unica</Gun_LMG_Unique.verbs.Verb_Shoot.label>
  
  <!-- EN: unique minigun -->
  <Gun_Minigun_Unique.label>minigun unico</Gun_Minigun_Unique.label>
  <!-- EN: A minigun with customized parts. -->
  <Gun_Minigun_Unique.description>Un minigun con parti personalizzate.</Gun_Minigun_Unique.description>
  <!-- EN: charge -->
  <Gun_Minigun_Unique.comps.CompEquippableAbilityReloadable.chargeNoun>carica</Gun_Minigun_Unique.comps.CompEquippableAbilityReloadable.chargeNoun>
  <!-- EN: on cooldown -->
  <Gun_Minigun_Unique.comps.CompEquippableAbilityReloadable.cooldownGerund>in ricarica</Gun_Minigun_Unique.comps.CompEquippableAbilityReloadable.cooldownGerund>
  <!-- EN: minigun -->
  <Gun_Minigun_Unique.comps.CompUniqueWeapon.namerLabels.0>minigun</Gun_Minigun_Unique.comps.CompUniqueWeapon.namerLabels.0>
  <!-- EN: gatling gun -->
  <Gun_Minigun_Unique.comps.CompUniqueWeapon.namerLabels.1>cannone Gatling</Gun_Minigun_Unique.comps.CompUniqueWeapon.namerLabels.1>
  <!-- EN: six-barrel -->
  <Gun_Minigun_Unique.comps.CompUniqueWeapon.namerLabels.2>a sei canne</Gun_Minigun_Unique.comps.CompUniqueWeapon.namerLabels.2>
  <!-- EN: barrels -->
  <Gun_Minigun_Unique.tools.barrels.label>canne</Gun_Minigun_Unique.tools.barrels.label>
  <!-- EN: unique minigun -->
  <Gun_Minigun_Unique.verbs.Verb_Shoot.label>minigun unico</Gun_Minigun_Unique.verbs.Verb_Shoot.label>
  
  <!-- EN: unique revolver -->
  <Gun_Revolver_Unique.label>revolver unico</Gun_Revolver_Unique.label>
  <!-- EN: A revolver with customized parts. -->
  <Gun_Revolver_Unique.description>Un revolver con parti personalizzate.</Gun_Revolver_Unique.description>
  <!-- EN: charge -->
  <Gun_Revolver_Unique.comps.CompEquippableAbilityReloadable.chargeNoun>carica</Gun_Revolver_Unique.comps.CompEquippableAbilityReloadable.chargeNoun>
  <!-- EN: on cooldown -->
  <Gun_Revolver_Unique.comps.CompEquippableAbilityReloadable.cooldownGerund>in ricarica</Gun_Revolver_Unique.comps.CompEquippableAbilityReloadable.cooldownGerund>
  <!-- EN: revolver -->
  <Gun_Revolver_Unique.comps.CompUniqueWeapon.namerLabels.0>revolver</Gun_Revolver_Unique.comps.CompUniqueWeapon.namerLabels.0>
  <!-- EN: six-shooter -->
  <Gun_Revolver_Unique.comps.CompUniqueWeapon.namerLabels.1>sei colpi</Gun_Revolver_Unique.comps.CompUniqueWeapon.namerLabels.1>
  <!-- EN: iron -->
  <Gun_Revolver_Unique.comps.CompUniqueWeapon.namerLabels.2>ferro</Gun_Revolver_Unique.comps.CompUniqueWeapon.namerLabels.2>
  <!-- EN: hammer -->
  <Gun_Revolver_Unique.comps.CompUniqueWeapon.namerLabels.3>martello</Gun_Revolver_Unique.comps.CompUniqueWeapon.namerLabels.3>
  <!-- EN: grip -->
  <Gun_Revolver_Unique.tools.grip.label>impugnatura</Gun_Revolver_Unique.tools.grip.label>
  <!-- EN: barrel -->
  <Gun_Revolver_Unique.tools.barrel.label>canna</Gun_Revolver_Unique.tools.barrel.label>
  <!-- EN: unique revolver -->
  <Gun_Revolver_Unique.verbs.Verb_Shoot.label>revolver unico</Gun_Revolver_Unique.verbs.Verb_Shoot.label>
  
  <!-- EN: unique sniper rifle -->
  <Gun_SniperRifle_Unique.label>fucile da cecchino unico</Gun_SniperRifle_Unique.label>
  <!-- EN: A sniper rifle with customized parts. -->
  <Gun_SniperRifle_Unique.description>Un fucile da cecchino con parti personalizzate.</Gun_SniperRifle_Unique.description>
  <!-- EN: charge -->
  <Gun_SniperRifle_Unique.comps.CompEquippableAbilityReloadable.chargeNoun>carica</Gun_SniperRifle_Unique.comps.CompEquippableAbilityReloadable.chargeNoun>
  <!-- EN: on cooldown -->
  <Gun_SniperRifle_Unique.comps.CompEquippableAbilityReloadable.cooldownGerund>in ricarica</Gun_SniperRifle_Unique.comps.CompEquippableAbilityReloadable.cooldownGerund>
  <!-- EN: sniper rifle -->
  <Gun_SniperRifle_Unique.comps.CompUniqueWeapon.namerLabels.0>fucile da cecchino</Gun_SniperRifle_Unique.comps.CompUniqueWeapon.namerLabels.0>
  <!-- EN: precision rifle -->
  <Gun_SniperRifle_Unique.comps.CompUniqueWeapon.namerLabels.1>fucile di precisione</Gun_SniperRifle_Unique.comps.CompUniqueWeapon.namerLabels.1>
  <!-- EN: marksman rifle -->
  <Gun_SniperRifle_Unique.comps.CompUniqueWeapon.namerLabels.2>fucile da tiratore scelto</Gun_SniperRifle_Unique.comps.CompUniqueWeapon.namerLabels.2>
  <!-- EN: sniper -->
  <Gun_SniperRifle_Unique.comps.CompUniqueWeapon.namerLabels.3>cecchino</Gun_SniperRifle_Unique.comps.CompUniqueWeapon.namerLabels.3>
  <!-- EN: headshotter -->
  <Gun_SniperRifle_Unique.comps.CompUniqueWeapon.namerLabels.4>tiratore alla testa</Gun_SniperRifle_Unique.comps.CompUniqueWeapon.namerLabels.4>
  <!-- EN: snipegun -->
  <Gun_SniperRifle_Unique.comps.CompUniqueWeapon.namerLabels.5>fucile da eliminazione</Gun_SniperRifle_Unique.comps.CompUniqueWeapon.namerLabels.5>
  <!-- EN: stalker -->
  <Gun_SniperRifle_Unique.comps.CompUniqueWeapon.namerLabels.6>predatore</Gun_SniperRifle_Unique.comps.CompUniqueWeapon.namerLabels.6>
  <!-- EN: assassinator -->
  <Gun_SniperRifle_Unique.comps.CompUniqueWeapon.namerLabels.7>assassino</Gun_SniperRifle_Unique.comps.CompUniqueWeapon.namerLabels.7>
  <!-- EN: stock -->
  <Gun_SniperRifle_Unique.tools.stock.label>calcio</Gun_SniperRifle_Unique.tools.stock.label>
  <!-- EN: barrel -->
  <Gun_SniperRifle_Unique.tools.barrel.label>canna</Gun_SniperRifle_Unique.tools.barrel.label>
  <!-- EN: unique sniper rifle -->
  <Gun_SniperRifle_Unique.verbs.Verb_Shoot.label>fucile da cecchino unico</Gun_SniperRifle_Unique.verbs.Verb_Shoot.label>
  
</LanguageData>