<?xml version='1.0' encoding='utf-8'?>
<LanguageData>
  
  
  <AcidSpray.label>spray acido</AcidSpray.label>
  
  <AcidSpray.description>I portatori sviluppano ghiandole nel collo che generano e immagazzinano una sostanza acida appiccicosa, insieme ai tessuti acido-tolleranti nella bocca. Possono spargere questo acido su un'area, dove si attaccherà ai nemici e li brucerà nel tempo.</AcidSpray.description>
  
  <AcidSpray.symbolPack.prefixSymbols.0.symbol>acido</AcidSpray.symbolPack.prefixSymbols.0.symbol>
  
  <AcidSpray.symbolPack.prefixSymbols.1.symbol>acero</AcidSpray.symbolPack.prefixSymbols.1.symbol>
  
  <AcidSpray.symbolPack.prefixSymbols.2.symbol>acri</AcidSpray.symbolPack.prefixSymbols.2.symbol>
  
  <AcidSpray.symbolPack.prefixSymbols.3.symbol>oxo</AcidSpray.symbolPack.prefixSymbols.3.symbol>
  
  <AcidSpray.symbolPack.suffixSymbols.0.symbol>spruzzatore</AcidSpray.symbolPack.suffixSymbols.0.symbol>
  
  <AcidSpray.symbolPack.suffixSymbols.1.symbol>sputatore</AcidSpray.symbolPack.suffixSymbols.1.symbol>
  
  
  <AnimalWarcall.label>richiamo di guerra animale</AnimalWarcall.label>
  
  <AnimalWarcall.description>I portatori di questo gene possono eseguire un richiamo di guerra animale, utilizzando un potente urlo e una connessione psichica per chiamare un animale a combattere per loro.</AnimalWarcall.description>
  
  <AnimalWarcall.symbolPack.prefixSymbols.0.symbol>guerra</AnimalWarcall.symbolPack.prefixSymbols.0.symbol>
  
  <AnimalWarcall.symbolPack.prefixSymbols.1.symbol>animale</AnimalWarcall.symbolPack.prefixSymbols.1.symbol>
  
  <AnimalWarcall.symbolPack.prefixSymbols.2.symbol>gridare</AnimalWarcall.symbolPack.prefixSymbols.2.symbol>
  
  <AnimalWarcall.symbolPack.suffixSymbols.0.symbol>chiamante</AnimalWarcall.symbolPack.suffixSymbols.0.symbol>
  
  <AnimalWarcall.symbolPack.suffixSymbols.1.symbol>banditore</AnimalWarcall.symbolPack.suffixSymbols.1.symbol>
  
  <AnimalWarcall.symbolPack.suffixSymbols.2.symbol>megafono</AnimalWarcall.symbolPack.suffixSymbols.2.symbol>
  
  <AnimalWarcall.symbolPack.wholeNameSymbols.0.symbol>warcaller</AnimalWarcall.symbolPack.wholeNameSymbols.0.symbol>
  
  
  <Bloodfeeder.label>mangiatore di sangue</Bloodfeeder.label>
  
  <Bloodfeeder.description>I portatori di questo gene hanno piccole zanne retrattili e un organo sul tetto della bocca che può estrarre l'emogeno dal sangue fresco e caldo. Possono mordere una persona che non resiste, succhiare il sangue e ottenere direttamente l'emogeno.</Bloodfeeder.description>
  
  <Bloodfeeder.symbolPack.prefixSymbols.0.symbol>eme</Bloodfeeder.symbolPack.prefixSymbols.0.symbol>
  
  <Bloodfeeder.symbolPack.prefixSymbols.1.symbol>sangue</Bloodfeeder.symbolPack.prefixSymbols.1.symbol>
  
  <Bloodfeeder.symbolPack.prefixSymbols.2.symbol>vampiro</Bloodfeeder.symbolPack.prefixSymbols.2.symbol>
  
  <Bloodfeeder.symbolPack.prefixSymbols.3.symbol>zanna</Bloodfeeder.symbolPack.prefixSymbols.3.symbol>
  
  <Bloodfeeder.symbolPack.suffixSymbols.0.symbol>zanna</Bloodfeeder.symbolPack.suffixSymbols.0.symbol>
  
  <Bloodfeeder.symbolPack.suffixSymbols.1.symbol>mangiatore</Bloodfeeder.symbolPack.suffixSymbols.1.symbol>
  
  <Bloodfeeder.symbolPack.suffixSymbols.2.symbol>autobus</Bloodfeeder.symbolPack.suffixSymbols.2.symbol>
  
  <Bloodfeeder.symbolPack.wholeNameSymbols.0.symbol>mangiatore di sangue</Bloodfeeder.symbolPack.wholeNameSymbols.0.symbol>
  
  
  <Coagulate.label>coagulare</Coagulate.label>
  
  <Coagulate.description>I portatori di questo gene hanno ghiandole speciali sulle mani e sui polsi, oltre a un composto salivare unico che possono utilizzare per curare rapidamente le ferite.</Coagulate.description>
  
  <Coagulate.labelShortAdj>coagulatore</Coagulate.labelShortAdj>
  
  <Coagulate.symbolPack.suffixSymbols.0.symbol>vita</Coagulate.symbolPack.suffixSymbols.0.symbol>
  
  <Coagulate.symbolPack.suffixSymbols.1.symbol>clotter</Coagulate.symbolPack.suffixSymbols.1.symbol>
  
  <Coagulate.symbolPack.suffixSymbols.2.symbol>tendere</Coagulate.symbolPack.suffixSymbols.2.symbol>
  
  
  <FireSpew.label>sputo di fuoco</FireSpew.label>
  
  <FireSpew.description>I portatori sono in grado di sputare bile infiammabile generata da un organo speciale nel collo. La bile si attacca a qualsiasi cosa in una piccola area e può incendiare persone, oggetti e il terreno.</FireSpew.description>
  
  <FireSpew.symbolPack.prefixSymbols.0.symbol>fuoco</FireSpew.symbolPack.prefixSymbols.0.symbol>
  
  <FireSpew.symbolPack.prefixSymbols.1.symbol>fiamma</FireSpew.symbolPack.prefixSymbols.1.symbol>
  
  <FireSpew.symbolPack.prefixSymbols.2.symbol>pira</FireSpew.symbolPack.prefixSymbols.2.symbol>
  
  <FireSpew.symbolPack.prefixSymbols.3.symbol>piro</FireSpew.symbolPack.prefixSymbols.3.symbol>
  
  <FireSpew.symbolPack.prefixSymbols.4.symbol>scintilla</FireSpew.symbolPack.prefixSymbols.4.symbol>
  
  <FireSpew.symbolPack.prefixSymbols.5.symbol>brace</FireSpew.symbolPack.prefixSymbols.5.symbol>
  
  <FireSpew.symbolPack.prefixSymbols.6.symbol>vomitare</FireSpew.symbolPack.prefixSymbols.6.symbol>
  
  <FireSpew.symbolPack.prefixSymbols.7.symbol>bruciare</FireSpew.symbolPack.prefixSymbols.7.symbol>
  
  <FireSpew.symbolPack.prefixSymbols.8.symbol>fuoco</FireSpew.symbolPack.prefixSymbols.8.symbol>
  
  <FireSpew.symbolPack.prefixSymbols.9.symbol>cenere</FireSpew.symbolPack.prefixSymbols.9.symbol>
  
  <FireSpew.symbolPack.prefixSymbols.10.symbol>Cenere</FireSpew.symbolPack.prefixSymbols.10.symbol>
  
  <FireSpew.symbolPack.suffixSymbols.0.symbol>Leggero</FireSpew.symbolPack.suffixSymbols.0.symbol>
  
  <FireSpew.symbolPack.suffixSymbols.1.symbol>bruciatore</FireSpew.symbolPack.suffixSymbols.1.symbol>
  
  <FireSpew.symbolPack.suffixSymbols.2.symbol>piro</FireSpew.symbolPack.suffixSymbols.2.symbol>
  
  <FireSpew.symbolPack.suffixSymbols.3.symbol>Cenere</FireSpew.symbolPack.suffixSymbols.3.symbol>
  
  <FireSpew.symbolPack.wholeNameSymbols.0.symbol>bruciatore</FireSpew.symbolPack.wholeNameSymbols.0.symbol>
  
  <FireSpew.symbolPack.wholeNameSymbols.1.symbol>accenditore</FireSpew.symbolPack.wholeNameSymbols.1.symbol>
  
  
  <FoamSpray.label>spruzzo di schiuma</FoamSpray.label>
  
  <FoamSpray.description>I portatori sviluppano ghiandole nel collo che generano e immagazzinano una schiuma ignifuga. Possono spargere questa schiuma su un'area per estinguere gli incendi.</FoamSpray.description>
  
  <FoamSpray.symbolPack.prefixSymbols.0.symbol>schiuma</FoamSpray.symbolPack.prefixSymbols.0.symbol>
  
  <FoamSpray.symbolPack.prefixSymbols.1.symbol>sputo</FoamSpray.symbolPack.prefixSymbols.1.symbol>
  
  <FoamSpray.symbolPack.prefixSymbols.2.symbol>spray</FoamSpray.symbolPack.prefixSymbols.2.symbol>
  
  <FoamSpray.symbolPack.prefixSymbols.3.symbol>schiuma</FoamSpray.symbolPack.prefixSymbols.3.symbol>
  
  <FoamSpray.symbolPack.prefixSymbols.4.symbol>crema</FoamSpray.symbolPack.prefixSymbols.4.symbol>
  
  <FoamSpray.symbolPack.prefixSymbols.5.symbol>da</FoamSpray.symbolPack.prefixSymbols.5.symbol>
  
  <FoamSpray.symbolPack.suffixSymbols.0.symbol>schiumatore</FoamSpray.symbolPack.suffixSymbols.0.symbol>
  
  <FoamSpray.symbolPack.suffixSymbols.1.symbol>Sud</FoamSpray.symbolPack.suffixSymbols.1.symbol>
  
  <FoamSpray.symbolPack.wholeNameSymbols.0.symbol>schiumatore</FoamSpray.symbolPack.wholeNameSymbols.0.symbol>
  
  
  <LongjumpLegs.label>gambe per il salto in lungo</LongjumpLegs.label>
  
  <LongjumpLegs.description>I portatori hanno speciali fibre muscolari alimentate dall'emogeno nelle gambe che consentono loro di saltare grandi distanze.</LongjumpLegs.description>
  
  <LongjumpLegs.symbolPack.prefixSymbols.0.symbol>salto</LongjumpLegs.symbolPack.prefixSymbols.0.symbol>
  
  <LongjumpLegs.symbolPack.prefixSymbols.1.symbol>salto</LongjumpLegs.symbolPack.prefixSymbols.1.symbol>
  
  <LongjumpLegs.symbolPack.prefixSymbols.2.symbol>volta</LongjumpLegs.symbolPack.prefixSymbols.2.symbol>
  
  <LongjumpLegs.symbolPack.prefixSymbols.3.symbol>lungo</LongjumpLegs.symbolPack.prefixSymbols.3.symbol>
  
  <LongjumpLegs.symbolPack.prefixSymbols.4.symbol>volare</LongjumpLegs.symbolPack.prefixSymbols.4.symbol>
  
  <LongjumpLegs.symbolPack.prefixSymbols.5.symbol>salto</LongjumpLegs.symbolPack.prefixSymbols.5.symbol>
  
  <LongjumpLegs.symbolPack.wholeNameSymbols.0.symbol>maglione</LongjumpLegs.symbolPack.wholeNameSymbols.0.symbol>
  
  <LongjumpLegs.symbolPack.wholeNameSymbols.1.symbol>saltatore</LongjumpLegs.symbolPack.wholeNameSymbols.1.symbol>
  
  <LongjumpLegs.symbolPack.wholeNameSymbols.2.symbol>buttafuori</LongjumpLegs.symbolPack.wholeNameSymbols.2.symbol>
  
  
  <PiercingSpine.label>piercing alla colonna vertebrale</PiercingSpine.label>
  
  <PiercingSpine.description>I portatori sviluppano un'apertura nella parte superiore del torace insieme a un fremito di spine di cheratina. Usando una reazione chimica alimentata dall'emogeno, possono sparare queste spine ad alta velocità contro bersagli vicini con sorprendente precisione.</PiercingSpine.description>
  
  <PiercingSpine.symbolPack.prefixSymbols.0.symbol>colonna vertebrale</PiercingSpine.symbolPack.prefixSymbols.0.symbol>
  
  <PiercingSpine.symbolPack.prefixSymbols.1.symbol>spina</PiercingSpine.symbolPack.prefixSymbols.1.symbol>
  
  <PiercingSpine.symbolPack.prefixSymbols.2.symbol>bullone</PiercingSpine.symbolPack.prefixSymbols.2.symbol>
  
  <PiercingSpine.symbolPack.wholeNameSymbols.0.symbol>spinatore</PiercingSpine.symbolPack.wholeNameSymbols.0.symbol>
  
  
  <XenogermReimplanter.label>impiantatore di geni</XenogermReimplanter.label>
  
  <XenogermReimplanter.description>I portatori di questo gene possono impiantare una copia del loro xenogerme in un'altra persona attraverso un organo iniettore dall'aspetto piuttosto grossolano. Il loro materiale genetico crescerà quindi molto lentamente. Se si impiantano mentre i loro geni stanno ricrescendo, moriranno. I geni germinali non saranno influenzati.</XenogermReimplanter.description>
  
  <XenogermReimplanter.labelShortAdj>reimpianto</XenogermReimplanter.labelShortAdj>
  
</LanguageData>