<?xml version="1.0" encoding="UTF-8"?>
<LanguageData>
  
  <!-- EN: orbital trader arrival -->
  <OrbitalTraderArrival.label>arrivo di un mercante orbitale</OrbitalTraderArrival.label>
  
  <!-- EN: enemy raid (special locations) -->
  <RaidEnemyBeacon.label>TODO</RaidEnemyBeacon.label>
  
  <!-- EN: friendly raid -->
  <RaidFriendly.label>spedizione alleata</RaidFriendly.label>
  
  <!-- EN: ship chunk drop -->
  <ShipChunkDrop.label>schianto parti di nave</ShipChunkDrop.label>
  
  <!-- EN: man in black -->
  <StrangerInBlackJoin.label>TODO</StrangerInBlackJoin.label>
  <!-- EN: Man in black -->
  <StrangerInBlackJoin.letterLabel>TODO</StrangerInBlackJoin.letterLabel>
  <!-- EN: Sensing trouble, a mysterious [PAWN_kind] has arrived.\n\nWill [PAWN_pronoun] be able to set things right in these parts? -->
  <StrangerInBlackJoin.letterText>TODO</StrangerInBlackJoin.letterText>
  
  <!-- EN: trader caravan arrival -->
  <TraderCaravanArrival.label>arrivo di una carovana commerciale</TraderCaravanArrival.label>
  
  <!-- EN: traveler group -->
  <TravelerGroup.label>gruppo di viaggiatori</TravelerGroup.label>
  
  <!-- EN: visitor group -->
  <VisitorGroup.label>gruppo di visitatori</VisitorGroup.label>
  
</LanguageData>